WTForms_SQLAlchemy_mlenzen-0.2.dist-info/METADATA
WTForms_SQLAlchemy_mlenzen-0.2.dist-info/RECORD
WTForms_SQLAlchemy_mlenzen-0.2.dist-info/WHEEL
WTForms_SQLAlchemy_mlenzen-0.2.dist-info/top_level.txt
wtforms_sqlalchemy/__init__.py
wtforms_sqlalchemy/fields.py
wtforms_sqlalchemy/orm.py
