Metadata-Version: 2.1
Name: WTForms-SQLAlchemy-mlenzen
Version: 0.2
Summary: SQLAlchemy tools for WTForms
Home-page: http://github.com/mlenzen/wtforms-sqlalchemy/
Author: Thomas Johansson, James Crasta, Michael Lenzen
Author-email: m.lenzen@gmail.com
License: BSD
Platform: UNKNOWN
Classifier: Development Status :: 5 - Production/Stable
Classifier: Environment :: Web Environment
Classifier: Intended Audience :: Developers
Classifier: License :: OSI Approved :: BSD License
Classifier: Operating System :: OS Independent
Classifier: Programming Language :: Python
Classifier: Programming Language :: Python :: 2.7
Classifier: Programming Language :: Python :: 3
Classifier: Programming Language :: Python :: 3.4
Classifier: Programming Language :: Python :: 3.5
Classifier: Programming Language :: Python :: 3.6
Classifier: Programming Language :: Python :: 3.7
Classifier: Programming Language :: Python :: 3.8
Classifier: Topic :: Internet :: WWW/HTTP :: Dynamic Content
Classifier: Topic :: Software Development :: Libraries :: Python Modules
Requires-Dist: WTForms (>=1.0.5)
Requires-Dist: SQLAlchemy (>=0.7.10)
